[
  {
    "text": "no i want halal food",
    "intent": "deny",
    "intent_prediction": {
      "name": "inform",
      "confidence": 0.9884418845176697
    }
  },
  {
    "text": "correct",
    "intent": "affirm",
    "intent_prediction": {
      "name": "inform",
      "confidence": 1.0
    }
  },
  {
    "text": "id like a restaurant in any area that it serves canapes",
    "intent": "inform",
    "intent_prediction": {
      "name": "affirm",
      "confidence": 0.8842276334762573
    }
  },
  {
    "text": "serves british food",
    "intent": "inform",
    "intent_prediction": {
      "name": "deny",
      "confidence": 0.8664258718490601
    }
  },
  {
    "text": "brazilian food",
    "intent": "inform",
    "intent_prediction": {
      "name": "affirm",
      "confidence": 0.9975889325141907
    }
  }
]