[
  {
    "text": "id like an expensive restaurant that serves mediteranean food",
    "entities": [
      {
        "start": 11,
        "end": 20,
        "value": "expensive",
        "entity": "price"
      }
    ],
    "predicted_entities": [
      {
        "entity": "price",
        "start": 11,
        "end": 20,
        "confidence_entity": 0.9998409748077393,
        "value": "hi",
        "extractor": "DIETClassifier",
        "processors": [
          "EntitySynonymMapper"
        ]
      },
      {
        "entity": "cuisine",
        "start": 44,
        "end": 56,
        "confidence_entity": 0.9998152852058411,
        "value": "mediteranean",
        "extractor": "DIETClassifier"
      }
    ]
  },
  {
    "text": "um i dont care i just want traditional food",
    "entities": [
      {
        "start": 27,
        "end": 38,
        "value": "traditional",
        "entity": "cuisine"
      }
    ],
    "predicted_entities": [
      {
        "entity": "cuisine",
        "start": 17,
        "end": 21,
        "confidence_entity": 0.6448054909706116,
        "value": "just",
        "extractor": "DIETClassifier"
      },
      {
        "entity": "cuisine",
        "start": 27,
        "end": 38,
        "confidence_entity": 0.9997938275337219,
        "value": "traditional",
        "extractor": "DIETClassifier"
      }
    ]
  },
  {
    "text": "cheap restaurant that serves german food",
    "entities": [
      {
        "start": 0,
        "end": 5,
        "value": "cheap",
        "entity": "price"
      },
      {
        "start": 29,
        "end": 35,
        "value": "german",
        "entity": "cuisine"
      }
    ],
    "predicted_entities": [
      {
        "entity": "price",
        "start": 0,
        "end": 5,
        "confidence_entity": 0.9995478987693787,
        "value": "lo",
        "extractor": "DIETClassifier",
        "processors": [
          "EntitySynonymMapper"
        ]
      }
    ]
  },
  {
    "text": "how about an indian restaurant in the north part of town",
    "entities": [
      {
        "start": 13,
        "end": 19,
        "value": "indian",
        "entity": "cuisine"
      }
    ],
    "predicted_entities": [
      {
        "entity": "cuisine",
        "start": 13,
        "end": 19,
        "confidence_entity": 0.9998443126678467,
        "value": "indian",
        "extractor": "DIETClassifier"
      },
      {
        "entity": "location",
        "start": 38,
        "end": 43,
        "confidence_entity": 0.9979206919670105,
        "value": "north",
        "extractor": "DIETClassifier"
      }
    ]
  },
  {
    "text": "im looking for a restaurant on the east part of town that serves scandinavia food",
    "entities": [
      {
        "start": 35,
        "end": 39,
        "value": "east",
        "entity": "location"
      }
    ],
    "predicted_entities": [
      {
        "entity": "location",
        "start": 35,
        "end": 39,
        "confidence_entity": 0.9997733235359192,
        "value": "east",
        "extractor": "DIETClassifier"
      },
      {
        "entity": "cuisine",
        "start": 65,
        "end": 76,
        "confidence_entity": 0.9998965263366699,
        "value": "scandinavia",
        "extractor": "DIETClassifier"
      }
    ]
  },
  {
    "text": "im looking for a restaurant in any area that serves bistro food",
    "entities": [
      {
        "start": 52,
        "end": 58,
        "value": "bistro",
        "entity": "cuisine"
      }
    ],
    "predicted_entities": []
  },
  {
    "text": "how about an expensive restaurant that serves european food",
    "entities": [
      {
        "start": 46,
        "end": 54,
        "value": "european",
        "entity": "cuisine"
      }
    ],
    "predicted_entities": [
      {
        "entity": "price",
        "start": 13,
        "end": 22,
        "confidence_entity": 0.9998335838317871,
        "value": "hi",
        "extractor": "DIETClassifier",
        "processors": [
          "EntitySynonymMapper"
        ]
      },
      {
        "entity": "cuisine",
        "start": 46,
        "end": 54,
        "confidence_entity": 0.9735093116760254,
        "value": "european",
        "extractor": "DIETClassifier"
      }
    ]
  },
  {
    "text": "id like a restaurant in the north part of town that serves cross over food",
    "entities": [
      {
        "start": 28,
        "end": 33,
        "value": "north",
        "entity": "location"
      }
    ],
    "predicted_entities": [
      {
        "entity": "location",
        "start": 28,
        "end": 33,
        "confidence_entity": 0.9990575909614563,
        "value": "north",
        "extractor": "DIETClassifier"
      },
      {
        "entity": "cuisine",
        "start": 59,
        "end": 64,
        "confidence_entity": 0.9990665316581726,
        "value": "cross",
        "extractor": "DIETClassifier"
      }
    ]
  },
  {
    "text": "im looking for a restaurant in the west part of town that serves canape food",
    "entities": [
      {
        "start": 35,
        "end": 39,
        "value": "west",
        "entity": "location"
      }
    ],
    "predicted_entities": [
      {
        "entity": "location",
        "start": 35,
        "end": 39,
        "confidence_entity": 0.9998053908348083,
        "value": "west",
        "extractor": "DIETClassifier"
      },
      {
        "entity": "cuisine",
        "start": 65,
        "end": 71,
        "confidence_entity": 0.9992226362228394,
        "value": "canape",
        "extractor": "DIETClassifier"
      }
    ]
  }
]